lowess_grouped/__init__.py
lowess_grouped/lowess_grouped.py
lowess_grouped-0.0.7.dist-info/METADATA
lowess_grouped-0.0.7.dist-info/WHEEL
lowess_grouped-0.0.7.dist-info/licenses/LICENSE
lowess_grouped-0.0.7.dist-info/RECORD
