Metadata-Version: 2.1
Name: lowess_grouped
Version: 0.0.7
Summary: Apply groupwise lowess smoothing to a dataframe
Project-URL: Source Code, https://github.com/lukiwieser/lowess-grouped
Project-URL: Bug Tracker, https://github.com/lukiwieser/lowess-grouped/issues
Author: Lukas Wieser
License-File: LICENSE
Classifier: License :: OSI Approved :: MIT License
Classifier: Operating System :: OS Independent
Classifier: Programming Language :: Python :: 3
Requires-Python: >=3.8
Requires-Dist: pandas>=1.1.5
Requires-Dist: statsmodels>=0.12.2
